errors/__init__.py
instagram/__init__.py
instagram/instagram_service.py
instagram/response.py
system/__init__.py
system/file_dialog.py
wordpress/__init__.py
wordpress/response.py
wordpress/wordpress_service.py
cystechpost-1.0.1.dist-info/COPYING.txt
cystechpost-1.0.1.dist-info/METADATA
cystechpost-1.0.1.dist-info/WHEEL
cystechpost-1.0.1.dist-info/top_level.txt
cystechpost-1.0.1.dist-info/RECORD
